python_midjourney/__init__.py
python_midjourney/client.py
python_midjourney/utils/__init__.py
python_midjourney-1.0.0.dist-info/licenses/LICENSE
python_midjourney-1.0.0.dist-info/METADATA
python_midjourney-1.0.0.dist-info/WHEEL
python_midjourney-1.0.0.dist-info/top_level.txt
python_midjourney-1.0.0.dist-info/RECORD
