Metadata-Version: 2.4
Name: python_midjourney
Version: 1.0.0
Summary: Midjourney automation system using Discord user tokens
Home-page: https://github.com/ooeunoo/python_midjourney
Author: ooeunoo
Author-email: seongeun.cho.dev@gmail.com
License: MIT
Project-URL: Bug Reports, https://github.com/ooeunoo/python_midjourney/issues
Project-URL: Source, https://github.com/ooeunoo/python_midjourney
Project-URL: Documentation, https://github.com/ooeunoo/python_midjourney#readme
Keywords: midjourney discord automation image generation ai art
Classifier: Development Status :: 4 - Beta
Classifier: Intended Audience :: Developers
Classifier: Operating System :: OS Independent
Classifier: Programming Language :: Python :: 3
Classifier: Programming Language :: Python :: 3.7
Classifier: Programming Language :: Python :: 3.8
Classifier: Programming Language :: Python :: 3.9
Classifier: Programming Language :: Python :: 3.10
Classifier: Programming Language :: Python :: 3.11
Classifier: Topic :: Software Development :: Libraries :: Python Modules
Classifier: Topic :: Communications :: Chat
Classifier: Topic :: Multimedia :: Graphics
Requires-Python: >=3.7
License-File: LICENSE
Requires-Dist: requests>=2.25.0
Requires-Dist: Pillow>=8.0.0
Provides-Extra: dev
Requires-Dist: pytest>=6.0; extra == "dev"
Requires-Dist: black>=21.0; extra == "dev"
Requires-Dist: flake8>=3.8; extra == "dev"
Dynamic: author
Dynamic: author-email
Dynamic: classifier
Dynamic: description
Dynamic: description-content-type
Dynamic: home-page
Dynamic: keywords
Dynamic: license
Dynamic: license-file
Dynamic: project-url
Dynamic: provides-extra
Dynamic: requires-dist
Dynamic: requires-python
Dynamic: summary
